[
  {
    "slug": "twitter",
    "label": "Follow me on Twitter",
    "url": "https://twitter.com/trepanation"
  },
  {
    "slug": "instagram",
    "label": "View my Instagram",
    "url": "https://www.instagram.com/trepanationpray"
  },
  {
    "slug": "dribbble",
    "label": "View my shots on Dribbble",
    "url": "https://dribbble.com/steven-hill"
  },
  {
    "slug": "github",
    "label": "View my commits",
    "url": "https://github.com/trepanation-pray"
  },
  {
    "slug": "linkedin",
    "label": "Connect with me on Linkedin",
    "url": "https://www.linkedin.com/in/steve-hill-design-code"
  }
]